mopidyapi/__init__.py
mopidyapi/client.py
mopidyapi/exceptions.py
mopidyapi/parsedata.py
mopidyapi/wsclient.py
mopidyapi/controllers/__init__.py
mopidyapi/controllers/history.py
mopidyapi/controllers/library.py
mopidyapi/controllers/mixer.py
mopidyapi/controllers/playback.py
mopidyapi/controllers/playlists.py
mopidyapi/controllers/tracklist.py
mopidyapi-1.1.0.dist-info/LICENSE
mopidyapi-1.1.0.dist-info/WHEEL
mopidyapi-1.1.0.dist-info/METADATA
mopidyapi-1.1.0.dist-info/RECORD
