Metadata-Version: 2.1
Name: mopidyapi
Version: 1.1.0
Summary: MopidyAPI
Home-page: https://github.com/AsbjornOlling/mopidyapi
Author: Asbjørn Olling
Author-email: asbjornolling@gmail.com
Requires-Python: >=3.6
Classifier: License :: OSI Approved :: GNU General Public License v3 or later (GPLv3+)
Classifier: Development Status :: 4 - Beta
Classifier: Intended Audience :: Developers
Classifier: Programming Language :: Python :: 3 :: Only
Classifier: Programming Language :: Python :: 3.6
Classifier: Topic :: Multimedia :: Sound/Audio :: Players
Classifier: Topic :: Software Development :: Libraries
Requires-Dist: requests
Requires-Dist: websockets
